sortty.py
sortty-0.0.3.dist-info/LICENSE.txt
sortty-0.0.3.dist-info/METADATA
sortty-0.0.3.dist-info/WHEEL
sortty-0.0.3.dist-info/top_level.txt
sortty-0.0.3.dist-info/RECORD
