Metadata-Version: 2.1
Name: sortty
Version: 0.0.3
Summary: Simple combination of advanced sorters
Home-page: https://github.com/yytrofimov/Sortty
Author-email: yytrofimov@gmail.com
License: UNKNOWN
Platform: UNKNOWN
Classifier: Programming Language :: Python :: 3
Classifier: License :: OSI Approved :: MIT License
Classifier: Operating System :: OS Independent
License-File: LICENSE.txt
